decree/__init__.py
decree/__main__.py
decree/cli.py
decree/core.py
decree/exitcodes.py
decree/models.py
decree/templates.py
decree/title.py
decree/utils.py
decree-0.2.0.dist-info/WHEEL
decree-0.2.0.dist-info/entry_points.txt
decree-0.2.0.dist-info/METADATA
decree-0.2.0.dist-info/RECORD
