Metadata-Version: 2.3
Name: decree
Version: 0.2.0
Summary: Decree: Python 3.11+ reimplementation of adr-tools with a typed API and Typer CLI.
Author: Steven Cutting
License: BSD-3-Clause
Classifier: License :: OSI Approved :: BSD License
Classifier: Programming Language :: Python :: 3
Classifier: Programming Language :: Python :: 3.11
Classifier: Programming Language :: Python :: 3.12
Classifier: Programming Language :: Python :: 3.13
Classifier: Environment :: Console
Classifier: Topic :: Documentation
Requires-Dist: typer>=0.12.0
Requires-Dist: beartype>=0.18.5
Requires-Dist: boltons>=25.0.0
Requires-Dist: pytest>=8.2 ; extra == 'dev'
Requires-Dist: pytest-cov>=5.0 ; extra == 'dev'
Requires-Dist: coverage>=7.6 ; extra == 'dev'
Requires-Dist: nox>=2024.4.15 ; extra == 'dev'
Requires-Dist: ruff>=0.6.9 ; extra == 'dev'
Requires-Dist: mypy>=1.11 ; extra == 'dev'
Requires-Dist: types-setuptools ; extra == 'dev'
Requires-Dist: types-python-dateutil ; extra == 'dev'
Requires-Dist: pymarkdownlnt>=0.9.17 ; extra == 'dev'
Requires-Python: >=3.11
Provides-Extra: dev
